mereswine/__init__.py
mereswine/assets.py
mereswine/cli.py
mereswine/core.py
mereswine/crawler.py
mereswine/factory.py
mereswine/menu.py
mereswine/mereswine.wsgi
mereswine/tasks.py
mereswine/utils.py
mereswine/api/__init__.py
mereswine/api/instance.py
mereswine/models/__init__.py
mereswine/models/instance.py
mereswine/static/logo.png
mereswine/static/.webassets-cache/027934a827711ea43657e425e5bb737f
mereswine/static/.webassets-cache/0da88630b3670253e5dfc0f632fdf1eb
mereswine/static/.webassets-cache/0df278c89f12f164c31b56cd5dd37d4a
mereswine/static/.webassets-cache/4a5abbb70869f1b6346435ad5418946f
mereswine/static/.webassets-cache/4d74e5c5de4397de8a997cf74acb79f8
mereswine/static/.webassets-cache/5b534943a3e45cb86470746326183d34
mereswine/static/.webassets-cache/7b861987a78274b8eaad496324bbdc23
mereswine/static/.webassets-cache/822377ceb306de5147902bbd0bf366c3
mereswine/static/.webassets-cache/9f53ded59f21eb86bc01b84d8b5b5c7b
mereswine/static/.webassets-cache/a665e8dffc7588e4d2c35874a5c025cc
mereswine/static/.webassets-cache/ac084891acdb3227207dc206805e1737
mereswine/static/.webassets-cache/c589a5c94e0e820ab34212494d603831
mereswine/static/.webassets-cache/cf9b8e80205bb1e100a1618cbb7fc3d6
mereswine/static/.webassets-cache/e1324c8ffbb092a16959c172bdc97b6a
mereswine/static/.webassets-cache/e5cf65916b801095b3c3bf7010b1855c
mereswine/static/assets/bundle.css
mereswine/static/assets/bundle.js
mereswine/static/assets/statistics.css
mereswine/static/assets/statistics.js
mereswine/static/css/jquery-jvectormap-1.2.2.css
mereswine/static/css/jquery.jqplot.css
mereswine/static/css/main.scss
mereswine/static/js/jquery.js
mereswine/static/js/main.js
mereswine/static/js/jqplot/jquery.jqplot.js
mereswine/static/js/jqplot/plugins/jqplot.BezierCurveRenderer.js
mereswine/static/js/jqplot/plugins/jqplot.BezierCurveRenderer.min.js
mereswine/static/js/jqplot/plugins/jqplot.barRenderer.js
mereswine/static/js/jqplot/plugins/jqplot.barRenderer.min.js
mereswine-1.0rc2.dist-info/LICENSE
mereswine-1.0rc2.dist-info/METADATA
mereswine-1.0rc2.dist-info/WHEEL
mereswine-1.0rc2.dist-info/entry_points.txt
mereswine-1.0rc2.dist-info/top_level.txt
mereswine-1.0rc2.dist-info/RECORD
