Metadata-Version: 2.1
Name: mereswine
Version: 1.0rc2
Summary: UNKNOWN
Home-page: https://github.com/indico/mereswine
Author: UNKNOWN
Author-email: UNKNOWN
License: UNKNOWN
Platform: UNKNOWN
Requires-Dist: Babel (==2.7.0)
Requires-Dist: Flask (==1.1.1)
Requires-Dist: Flask-Assets (==0.12)
Requires-Dist: Flask-Babel (==0.12.2)
Requires-Dist: Flask-Mail (==0.9.1)
Requires-Dist: Flask-Multipass (>=0.0.dev4)
Requires-Dist: Flask-OAuthlib (==0.9.5)
Requires-Dist: Flask-SQLAlchemy (==2.4.0)
Requires-Dist: Flask-WTF (==0.14.2)
Requires-Dist: WTForms (==2.2.1)
Requires-Dist: Jinja2 (==2.10.1)
Requires-Dist: SQLAlchemy (==1.3.7)
Requires-Dist: Werkzeug (==0.15.5)
Requires-Dist: celery (==4.3.0)
Requires-Dist: csscompressor (==0.9.5)
Requires-Dist: hiredis (==1.0.0)
Requires-Dist: pytz
Requires-Dist: redis (==3.3.8)
Requires-Dist: requests (==2.22.0)
Requires-Dist: requests-oauthlib (<1.2.0)
Requires-Dist: webassets (==0.12.1)
Requires-Dist: psycopg2 (==2.8.3)
Requires-Dist: libsass (==0.19.2)
Requires-Dist: IPython
Requires-Dist: flask-shell-ipython
Requires-Dist: mondrian (==0.8.0)
